imputr/__init__.py
imputr/_constants.py
imputr/domain/__init__.py
imputr/domain/column.py
imputr/domain/table.py
imputr/domain/types.py
imputr/imputers/__init__.py
imputr/imputers/_base.py
imputr/imputers/autoimputer.py
imputr/imputers/meanimputer.py
imputr/strategy/__init__.py
imputr/strategy/_base.py
imputr/strategy/mean.py
imputr/strategy/randomforest.py
imputr-0.1.0.dist-info/LICENSE
imputr-0.1.0.dist-info/WHEEL
imputr-0.1.0.dist-info/METADATA
imputr-0.1.0.dist-info/RECORD
