Metadata-Version: 2.1
Name: imputr
Version: 0.1.0
Summary: Imputing missing values in your data science.
License: Apache-2.0
Author: Rauf Akdemir
Author-email: orhanrauf@gmail.com
Requires-Python: >=3.7.1,<3.11
Classifier: Development Status :: 2 - Pre-Alpha
Classifier: Intended Audience :: Developers
Classifier: Intended Audience :: Science/Research
Classifier: License :: OSI Approved :: Apache Software License
Classifier: Operating System :: POSIX :: Linux
Classifier: Operating System :: Unix
Classifier: Programming Language :: Python :: 3
Classifier: Programming Language :: Python :: 3.8
Classifier: Programming Language :: Python :: 3.9
Classifier: Programming Language :: Python :: 3.10
Classifier: Programming Language :: Python :: 3.10
Classifier: Programming Language :: Python :: 3.7
Classifier: Programming Language :: Python :: 3.8
Classifier: Programming Language :: Python :: 3.9
Classifier: Topic :: Internet
Classifier: Topic :: Software Development :: Libraries :: Python Modules
Requires-Dist: pandas (>=1.3,<2.0)
Requires-Dist: scikit-learn (>=1.0.2,<2.0.0)
Project-URL: Homepage, https://github.com/imputr/imputr
Project-URL: Source, https://github.com/imputr/imputr
Project-URL: Tracker, https://github.com/imputr/imputr/issues
